odoo/addons/partner_analytic/README.rst
odoo/addons/partner_analytic/__init__.py
odoo/addons/partner_analytic/__manifest__.py
odoo/addons/partner_analytic/i18n/es.po
odoo/addons/partner_analytic/i18n/partner_analytic.pot
odoo/addons/partner_analytic/models/__init__.py
odoo/addons/partner_analytic/models/account_move.py
odoo/addons/partner_analytic/models/res_partner.py
odoo/addons/partner_analytic/readme/CONTRIBUTORS.rst
odoo/addons/partner_analytic/readme/DESCRIPTION.rst
odoo/addons/partner_analytic/readme/USAGE.rst
odoo/addons/partner_analytic/static/description/icon.png
odoo/addons/partner_analytic/static/description/index.html
odoo/addons/partner_analytic/tests/__init__.py
odoo/addons/partner_analytic/tests/test_partner_analytic.py
odoo/addons/partner_analytic/views/partner_views.xml
odoo_addon_partner_analytic-15.0.1.0.0.5.dist-info/METADATA
odoo_addon_partner_analytic-15.0.1.0.0.5.dist-info/WHEEL
odoo_addon_partner_analytic-15.0.1.0.0.5.dist-info/top_level.txt
odoo_addon_partner_analytic-15.0.1.0.0.5.dist-info/RECORD
